[
  {
    "id": "1",
    "image": "https://darshan.ac.in/U01/Faculty-Photo/5---29-04-2023-11-00-29.jpg",
    "name": "Dr. Gopi Sanghani",
    "designation": "Dean - School of Computer Science",
    "education": "Ph.D. , M.E. (CE)",
    "experiance": "22+ Years",
    "joining": "Jul-2012"
  },
  {
    "id": "2",
    "image": "https://darshan.ac.in/U01/Faculty-Photo/3---28-04-2023-02-02-42.jpg",
    "name": "Dr. Nilesh Gambhava",
    "designation": "Professor",
    "education": "Ph.D. , M.E. (CE)",
    "experiance": "20+ Years",
    "joining": "Jul-2009"
  },
  {
    "id": "3",
    "image": "https://darshan.ac.in/U01/Faculty-Photo/6---28-04-2023-02-06-07.jpg",
    "name": "Dr. Pradyumansinh Jadeja",
    "designation": "Professor",
    "education": "Ph.D., M.E. (CE)",
    "experiance": "17+ Years",
    "joining": "Jul-2009"
  },
  {
    "id": "4",
    "image": "https://darshan.ac.in/U01/Faculty-Photo/8---28-04-2023-02-06-25.jpg",
    "name": "Prof. Maulik Trivedi",
    "designation": "Assistant Professor",
    "education": "Ph.D.(Pursuing), M.Tech.(CSE)",
    "experiance": "15+ Years",
    "joining": "Jun-2009"
  },
  {
    "id": " 5",
    "image": "https://darshan.ac.in/U01/Faculty-Photo/9---28-04-2023-02-06-37.jpg",
    "name": "Prof. Dixita Kagathara",
    "designation": "Assistant Professor",
    "education": "M.Tech. (Web Technology)",
    "experiance": "13+ Years",
    "joining": "Jul-2009"
  },
  {
    "id": "6",
    "image": "https://darshan.ac.in/U01/Faculty-Photo/12---28-04-2023-02-06-51.jpg",
    "name": "Prof. Firoz Sherasiya",
    "designation": "Assistant Professor",
    "education": "Ph.D.(Pursuing), M.E. (CE)",
    "experiance": "17+ Years",
    "joining": "Jul-2011"
  },
  {
    "id": "7",
    "image": "https://darshan.ac.in/U01/Faculty-Photo/10---28-04-2023-02-07-03.jpg",
    "name": "Prof. Rupesh Vaishnav",
    "designation": "Assistant Professor",
    "education": "Ph.D. (Pursuing), M.E. (CE)",
    "experiance": "15+ Years",
    "joining": "May-2013"
  },
  {
    "id": "8",
    "image": "https://darshan.ac.in/U01/Faculty-Photo/11---29-04-2023-01-44-21.jpg",
    "name": "Prof. Swati Sharma",
    "designation": "Assistant Professor",
    "education": "M.Tech. (CSE)",
    "experiance": "15+ Years",
    "joining": "May-2013"
  },
  {
    "id": "9",
    "image": "https://darshan.ac.in/U01/Faculty-Photo/15---28-04-2023-02-07-35.jpg",
    "name": "Prof. Arjun Bala",
    "designation": "Assistant Professor",
    "education": "Ph.D.(Pursuing), M.Tech.(CSE)",
    "experiance": "13+ Years",
    "joining": "Jul-2013"
  },
  {
    "id": "10",
    "image": "https://darshan.ac.in/U01/Faculty-Photo/13---28-04-2023-02-07-48.jpg",
    "name": "Prof. Mayur Padia",
    "designation": "Assistant Professor",
    "education": "M.E. (CE)",
    "experiance": "14+ Years",
    "joining": "Jul-2011"
  },
  {
    "id": "11",
    "image": "https://darshan.ac.in/U01/Faculty-Photo/16---28-04-2023-02-08-00.jpg",
    "name": "Prof. Vijay Shekhat",
    "designation": "Assistant Professor",
    "education": "M.E. (CE)",
    "experiance": "11+ Years",
    "joining": "Jun-2012"
  },
  {
    "id": "12",
    "image": "https://darshan.ac.in/U01/Faculty-Photo/220---28-04-2023-02-08-14.jpg",
    "name": "Prof. Ashok Badresiya",
    "designation": "Assistant Professor",
    "education": "M.E. (CE)",
    "experiance": "9+ Years",
    "joining": "Jul-2015"
  },
  {
    "id": "13",
    "image": "https://darshan.ac.in/U01/Faculty-Photo/214---28-04-2023-02-08-35.jpg",
    "name": "Prof. Naimish Vadodariya",
    "designation": "Assistant Professor",
    "education": "Ph.D. (Pursuing), M.E. (CE)",
    "experiance": "10+ Years",
    "joining": "Jun-2015"
  },
  {
    "id": "14",
    "image": "https://darshan.ac.in/U01/Faculty-Photo/221---28-04-2023-02-08-50.jpg",
    "name": "Prof. UmeshKumar Thoriya",
    "designation": "Assistant Professor",
    "education": "M.Tech. (CSE)",
    "experiance": "10+ Years",
    "joining": "Jul-2015"
  },
  {
    "id": "15",
    "image": "https://darshan.ac.in/U01/Faculty-Photo/219---28-04-2023-02-09-01.jpg",
    "name": "Prof. Jayesh Vagadiya",
    "designation": "Assistant Professor",
    "education": "M.E (CE)",
    "experiance": "7+ Years",
    "joining": "Jul-2015"
  },
  {
    "id": "16",
    "image": "https://darshan.ac.in/U01/Faculty-Photo/290---28-04-2023-02-09-16.jpg",
    "name": "Prof. Krunal Vyas",
    "designation": "Assistant Professor",
    "education": "M.Tech. (ICT)",
    "experiance": "9+ Years",
    "joining": "Jun-2018"
  },
  {
    "id": "17",
    "image": "https://darshan.ac.in/U01/Faculty-Photo/46---28-04-2023-02-09-28.jpg",
    "name": "Prof. Jay Dhamsaniya",
    "designation": "Assistant Professor",
    "education": "PG Diploma (Software Development), B.Tech. (E.C.)",
    "experiance": "10+ Years",
    "joining": "Jul-2012"
  },
  {
    "id": "18",
    "image": "https://darshan.ac.in/U01/Faculty-Photo/294---28-04-2023-02-09-43.jpg",
    "name": "Prof. Mehul Bhundiya",
    "designation": "Assistant Professor",
    "education": "BE (CE), ME (CE)",
    "experiance": "9+ Years",
    "joining": "Aug-2018"
  },
  {
    "id": "19",
    "image": "https://darshan.ac.in/U01/Faculty-Photo/317---28-04-2023-01-32-29.jpg",
    "name": "Prof. Vaseem Ghada",
    "designation": "Assistant Professor",
    "education": "Ph.D. (Pursuing), M.Tech (ICT)",
    "experiance": "13+ Years",
    "joining": "Aug-2021"
  },
  {
    "id": "20",
    "image": "https://darshan.ac.in/U01/Faculty-Photo/328---28-04-2023-01-33-05.jpg",
    "name": "Prof. Hemang Chath",
    "designation": "Assistant Professor",
    "education": "BE(CE), ME(CE - Pursuing)",
    "experiance": "12+ Years",
    "joining": "Sep-2021"
  },
  {
    "id": "21",
    "image": "https://darshan.ac.in/U01/Faculty-Photo/330---28-04-2023-01-33-25.jpg",
    "name": "Prof. Charvin Kothia",
    "designation": "Assistant Professor",
    "education": "B.E. [CE], M.Tech. [Software] (Pursuing)",
    "experiance": "3+ Years",
    "joining": "Nov-2020"
  },
  {
    "id": "22",
    "image": "https://darshan.ac.in/U01/Faculty-Photo/331---28-04-2023-01-33-39.jpg",
    "name": "Prof. Madhuresh Fichadiya",
    "designation": "Assistant Professor",
    "education": "B.E.(CE)",
    "experiance": "2+ Years",
    "joining": "Jul-2021"
  },
  {
    "id": "23",
    "image": "https://darshan.ac.in/U01/Faculty-Photo/334---28-04-2023-01-34-00.jpg",
    "name": "Prof. Vishal Kansagara",
    "designation": "Assistant Professor",
    "education": "M. TECH. (ICT)",
    "experiance": "9+ Years",
    "joining": "Nov-2021"
  },
  {
    "id": "24",
    "image": "https://darshan.ac.in/U01/Faculty-Photo/335---28-04-2023-01-34-15.jpg",
    "name": "Prof. Dharmik Vasiyani",
    "designation": "Assistant Professor",
    "education": "ME(CE)",
    "experiance": "5+ Years",
    "joining": "Nov-2021"
  },
  {
    "id": "25",
    "image": "https://darshan.ac.in/U01/Faculty-Photo/336---28-04-2023-01-34-37.jpg",
    "name": "Prof. Shruti Maniar",
    "designation": "Assistant Professor",
    "education": "ME(CE),BE(IT)",
    "experiance": "6+ Years",
    "joining": "Dec-2021"
  },
  {
    "id": "26",
    "image": "https://darshan.ac.in/U01/Faculty-Photo/358---28-04-2023-01-37-43.jpg",
    "name": "Prof. Bhushan Joshi",
    "designation": "Assistant Professor",
    "education": "M.E. (EC)",
    "experiance": "5+ Years",
    "joining": "Jun-2022"
  },
  {
    "id": "27",
    "image": "https://darshan.ac.in/U01/Faculty-Photo/362---28-04-2023-01-38-55.jpg",
    "name": "Prof. Kishankumar Jogi",
    "designation": "Assistant Professor",
    "education": "B.E.Electrical",
    "experiance": "8+ Years",
    "joining": "Aug-2022"
  },
  {
    "id": "28",
    "image": "https://darshan.ac.in/U01/Faculty-Photo/391---09-05-2023-12-45-38.jpg",
    "name": "Ms. Nidhi Chitroda",
    "designation": "Assistant Professor",
    "education": "M.Tech (CE)",
    "experiance": "8+ Years",
    "joining": "May-2023"
  },
  {
    "id": "29",
    "image": "https://darshan.ac.in/U01/Faculty-Photo/54---28-04-2023-01-43-14.jpg",
    "name": "Prof. Dipak Jivani",
    "designation": "Head of The Department",
    "education": "Ph.D (Pursuing), M.Tech. (CASAD), B.E. (Civil)",
    "experiance": "14+ Years",
    "joining": "Jan-2013"
  },
  {
    "id": "30",
    "image": "https://darshan.ac.in/U01/Faculty-Photo/131---29-04-2023-11-04-04.jpg",
    "name": "Prof. Mansukh Barasara",
    "designation": "Professor",
    "education": "M.E. (Civil), B.E. (Civil)",
    "experiance": "35+ Years",
    "joining": "Jun-2009"
  },
  {
    "id": "31",
    "image": "https://darshan.ac.in/U01/Faculty-Photo/53---28-04-2023-01-51-06.jpg",
    "name": "Dr. Ujjval Solanki",
    "designation": "Associate Professor",
    "education": "Ph.D., M.Tech. (Transportation Engineering), B.E. (Civil, AM...",
    "experiance": "33+ Years",
    "joining": "Jun-2009"
  },
  {
    "id": "32",
    "image": "https://darshan.ac.in/U01/Faculty-Photo/CIKCK_25052018_073554AM.jpg",
    "name": "Prof. Kaushik Koradia",
    "designation": "Associate Professor",
    "education": "Ph.D (Pursuing), M.E. (Structure), B.E. (Civil)",
    "experiance": "21+ Years",
    "joining": "Jul-2010"
  },
  {
    "id": "33",
    "image": "https://darshan.ac.in/U01/Faculty-Photo/37---28-04-2023-01-56-24.jpg",
    "name": "Prof. Chetan Solanki",
    "designation": "Assistant Professor",
    "education": "M.E. (Structure), B.E. (Civil), Diploma (Civil)",
    "experiance": "11+ Years",
    "joining": "Jun-2012"
  },
  {
    "id": "34",
    "image": "https://darshan.ac.in/U01/Faculty-Photo/55---28-04-2023-01-55-56.jpg",
    "name": "Prof. Vitrag Dholakia",
    "designation": "Assistant Professor",
    "education": "M.Sc. (Microbiology), B.Sc. (Microbiology), B.Ed",
    "experiance": "14+ Years",
    "joining": "Jul-2010"
  },
  {
    "id": "35",
    "image": "https://darshan.ac.in/U01/Faculty-Photo/217---28-04-2023-01-58-46.jpg",
    "name": "Prof. Akshar Fataniya",
    "designation": "Assistant Professor",
    "education": "M.Tech. (Construction Technology), B.E. (Civil), Diploma (Ci...",
    "experiance": "8+ Years",
    "joining": "Jun-2015"
  },
  {
    "id": "36",
    "image": "https://darshan.ac.in/U01/Faculty-Photo/274---28-04-2023-01-59-41.jpg",
    "name": "Prof. Chintan Raichura",
    "designation": "Assistant Professor",
    "education": "Ph.D (Pursuing), M.Tech. (Construction Technology), B.E. (Ci...",
    "experiance": "7+ Years",
    "joining": "Jun-2017"
  },
  {
    "id": "37",
    "image": "https://darshan.ac.in/U01/Faculty-Photo/61---28-04-2023-01-59-56.jpg",
    "name": "Prof. Milan Gohel",
    "designation": "Assistant Professor",
    "education": "M.E. (Chemical), B.E. (Chemical), Diploma (Chemical)",
    "experiance": "9+ Years",
    "joining": "May-2014"
  },
  {
    "id": "38",
    "image": "https://darshan.ac.in/U01/Faculty-Photo/313---28-04-2023-02-00-25.jpg",
    "name": "Prof. Ketan Abhani",
    "designation": "Assistant Professor",
    "education": "Ph.D (Pursuing), M.E. (Structure), B.E. (Civil)",
    "experiance": "4+ Years",
    "joining": "Mar-2021"
  },
  {
    "id": "39",
    "image": "https://darshan.ac.in/U01/Faculty-Photo/311---28-04-2023-02-00-39.jpg",
    "name": "Prof. Dhaval Jalalpara",
    "designation": "Assistant Professor",
    "education": "M.E. (Transportation), B.E. (Civil)",
    "experiance": "2+ Years",
    "joining": "Feb-2021"
  },
  {
    "id": "40",
    "image": "https://darshan.ac.in/U01/Faculty-Photo/371---28-04-2023-02-00-57.jpg",
    "name": "Prof. Deepkumar Hadvani",
    "designation": "Assistant Professor",
    "education": "M.E. (Structure), B.E. (Civil)",
    "experiance": "1+ Years",
    "joining": "Jul-2022"
  },
  {
    "id": "41",
    "image": "https://darshan.ac.in/U01/Faculty-Photo/235---28-04-2023-02-01-28.jpg",
    "name": "Prof. Sagar Galani",
    "designation": "Assistant Professor",
    "education": "B.E. (Civil)",
    "experiance": "7+ Years",
    "joining": "Jun-2016"
  },
  {
    "id": "42",
    "image": "https://darshan.ac.in/U01/Faculty-Photo/372---28-04-2023-02-03-21.jpg",
    "name": "Prof. Arjun Chavada",
    "designation": "Assistant Professor",
    "education": "B.E. (Civil)",
    "experiance": "1+ Years",
    "joining": "Jul-2022"
  },
  {
    "id": "43",
    "image": "https://darshan.ac.in/U01/Faculty-Photo/370---28-04-2023-02-03-38.jpg",
    "name": "Prof. Deepraj Patadia",
    "designation": "Assistant Professor",
    "education": "M.E. (Fracture Mechanics), B.E. (Civil)",
    "experiance": "2+ Years",
    "joining": "Sep-2022"
  },
  {
    "id": "44",
    "image": "https://darshan.ac.in/U01/Faculty-Photo/377---28-04-2023-02-03-52.jpg",
    "name": "Prof. Dhyey Mehta",
    "designation": "Assistant Professor",
    "education": "M.Tech. (Geotechnical Engineering), B.E. (Civil), Diploma (C...",
    "experiance": "1+ Years",
    "joining": "Dec-2022"
  },
  {
    "id": "45",
    "image": "https://darshan.ac.in/U01/Faculty-Photo/CIRRK01_25042019_023556PM.jpg",
    "name": "Mr. Rakesh Kanzariya",
    "designation": "Lab Assistant",
    "education": "B. E. (Civil)",
    "experiance": "6+ Years",
    "joining": "Mar-2018"
  },
  {
    "id": "46",
    "image": "https://darshan.ac.in/U01/Faculty-Photo/373---29-04-2023-11-02-24.jpg",
    "name": "Mr. Harsh Bharad",
    "designation": "Lab Assistant",
    "education": "M.Sc. (Environmental Science), B.Sc. ( Chemistry)",
    "experiance": "1+ Years",
    "joining": "Oct-2022"
  },
  {
    "id": "47",
    "image": "https://darshan.ac.in/U01/Faculty-Photo/376---08-05-2023-10-57-47.jpg",
    "name": "Mr. Bhautik  Kothari",
    "designation": "Lab Assistant",
    "education": "B.E. (Chemical)",
    "experiance": "0+ Years",
    "joining": "Oct-2022"
  },
  {
    "id": "48",
    "image": "https://darshan.ac.in/U01/Faculty-Photo/315---29-04-2023-11-00-13.jpg",
    "name": "Dr. Jignasa Mehta",
    "designation": "Dean - School of Engineering, Head",
    "education": "Ph.D. (Mechanical), M.E. (Machine Design), B.E. (Mechanical ...",
    "experiance": "27+ Years",
    "joining": "Jun-2021"
  },
  {
    "id": "49",
    "image": "https://darshan.ac.in/U01/Faculty-Photo/57---28-04-2023-01-45-32.jpg",
    "name": "Dr. Ashvin Makadia",
    "designation": "Professor",
    "education": "Ph.D. (Mechanical Engineering) , M.Tech. (CAD/CAM), B.E. (Me...",
    "experiance": "28+ Years",
    "joining": "May-2009"
  },
  {
    "id": "50",
    "image": "https://darshan.ac.in/U01/Faculty-Photo/64---28-04-2023-01-55-04.jpg",
    "name": "Prof. Bhavinkumar Vegada",
    "designation": "Assistant Professor",
    "education": "M.Tech. (Thermal Engineering), B.E. (Mechanical Engineering)...",
    "experiance": "12+ Years",
    "joining": "Jun-2011"
  },
  {
    "id": "51",
    "image": "https://darshan.ac.in/U01/Faculty-Photo/63---28-04-2023-01-56-09.jpg",
    "name": "Prof. Vimal Limbasiya",
    "designation": "Assistant Professor",
    "education": "M.Tech. (CAD/CAM), B.E. (Mechanical Engineering)",
    "experiance": "11+ Years",
    "joining": "Jul-2011"
  },
  {
    "id": "52",
    "image": "https://darshan.ac.in/U01/Faculty-Photo/66---28-04-2023-02-02-29.jpg",
    "name": "Prof. Ankur Tank",
    "designation": "Assistant Professor",
    "education": "B.E. (Mechanical Engineering)",
    "experiance": "11+ Years",
    "joining": "Aug-2011"
  },
  {
    "id": "53",
    "image": "https://darshan.ac.in/U01/Faculty-Photo/83---28-04-2023-02-03-02.jpg",
    "name": "Prof. Paras Vegada",
    "designation": "Assistant Professor",
    "education": "M.Tech (Pursuing),B.E. (Mechanical Engineering)",
    "experiance": "12+ Years",
    "joining": "Jul-2013"
  },
  {
    "id": "54",
    "image": "https://darshan.ac.in/U01/Faculty-Photo/73---28-04-2023-02-04-22.jpg",
    "name": "Prof. Sagar Kanjiya",
    "designation": "Assistant Professor",
    "education": "M.E. (Thermal Engineering), B.E. (Mechanical Engineering)",
    "experiance": "9+ Years",
    "joining": "Jun-2014"
  },
  {
    "id": "55",
    "image": "https://darshan.ac.in/U01/Faculty-Photo/326---28-04-2023-02-04-38.jpg",
    "name": "Prof. Yash Tank",
    "designation": "Assistant Professor",
    "education": "M.Tech. (Manufacturing Engineering), B.E. (Mechanical Engine...",
    "experiance": "3+ Years",
    "joining": "Aug-2021"
  },
  {
    "id": "56",
    "image": "https://darshan.ac.in/U01/Faculty-Photo/112---29-04-2023-11-01-08.jpg",
    "name": "Prof. Kartikraj Dhamsaniya",
    "designation": "Head of The Department",
    "education": "M.Phil. Mathematics, M.Sc. Applied Mathematics",
    "experiance": "12+ Years",
    "joining": "Jun-2011"
  },
  {
    "id": "57",
    "image": "https://darshan.ac.in/U01/Faculty-Photo/117---28-04-2023-01-58-13.jpg",
    "name": "Prof. Nishant Khiraiya",
    "designation": "Assistant Professor",
    "education": "M.Phil. Mathematics, M.Sc. Mathematics",
    "experiance": "9+ Years",
    "joining": "Jul-2013"
  },
  {
    "id": "58",
    "image": "https://darshan.ac.in/U01/Faculty-Photo/216---29-04-2023-11-01-47.jpg",
    "name": "Prof. Daxa Jani",
    "designation": "Assistant Professor",
    "education": "Ph.D. (Pursuing),    M.Phil. Mathematics",
    "experiance": "8+ Years",
    "joining": "Jul-2015"
  },
  {
    "id": "59",
    "image": "https://darshan.ac.in/U01/Faculty-Photo/298---10-05-2023-11-20-06.jpg",
    "name": "Prof. Dhvanik Zala",
    "designation": "Assistant Professor",
    "education": "M.Phil. Mathematics, M.Sc. Mathematics",
    "experiance": "3+ Years",
    "joining": "Nov-2022"
  },
  {
    "id": "60",
    "image": "https://darshan.ac.in/U01/Faculty-Photo/306---28-04-2023-02-01-11.jpg",
    "name": "Prof. Vishal Vadgama",
    "designation": "Assistant Professor",
    "education": "Ph.D. (Pursuing), M.Phil. Physics",
    "experiance": "4+ Years",
    "joining": "Sep-2020"
  },
  {
    "id": "61",
    "image": "https://darshan.ac.in/U01/Faculty-Photo/338---28-04-2023-02-01-43.jpg",
    "name": "Dr. Khushal Sagapariya",
    "designation": "Assistant Professor",
    "education": "Ph.D. Physics, M.Phil. Physics",
    "experiance": "6+ Years",
    "joining": "Sep-2021"
  },
  {
    "id": "62",
    "image": "https://darshan.ac.in/U01/Faculty-Photo/337---28-04-2023-02-02-11.jpg",
    "name": "Prof. Prashant Bakotiya",
    "designation": "Assistant Professor",
    "education": "M.Sc. Mathematics",
    "experiance": "4+ Years",
    "joining": "Oct-2021"
  },
  {
    "id": "63",
    "image": "https://darshan.ac.in/U01/Faculty-Photo/351---29-04-2023-01-48-01.jpg",
    "name": "Prof. Dhara  Bhut",
    "designation": "Assistant Professor",
    "education": "M.Sc. Mathematics",
    "experiance": "3+ Years",
    "joining": "Jun-2022"
  },
  {
    "id": "64",
    "image": "https://darshan.ac.in/U01/Faculty-Photo/357---28-04-2023-02-04-52.jpg",
    "name": "Prof. Vasudev  Barjadiya",
    "designation": "Assistant Professor",
    "education": "M.Sc. Mathematics",
    "experiance": "0+ Years",
    "joining": "Jul-2022"
  },
  {
    "id": "65",
    "image": "https://darshan.ac.in/U01/Faculty-Photo/356---28-04-2023-02-05-11.jpg",
    "name": "Prof. Priyanka Bharadiya",
    "designation": "Assistant Professor",
    "education": "M.Phil. Mathematics, M.Sc. Mathematics",
    "experiance": "10+ Years",
    "joining": "Jul-2022"
  },
  {
    "id": "66",
    "image": "https://darshan.ac.in/U01/Faculty-Photo/369---29-04-2023-01-10-13.jpg",
    "name": "Prof. Sneha Mundadiya",
    "designation": "Assistant Professor",
    "education": "Ph.D. (Pursuing), M.Sc. Pure Mathematics",
    "experiance": "7+ Years",
    "joining": "Sep-2022"
  },
  {
    "id": "67",
    "image": "https://darshan.ac.in/U01/Faculty-Photo/262---09-05-2023-12-40-29.jpg",
    "name": "Prof. Darshan Pipaliya",
    "designation": "Assistant Professor",
    "education": "GSET, M.Phil. Mathematics",
    "experiance": "5+ Years",
    "joining": "Mar-2023"
  },
  {
    "id": "68",
    "image": "https://darshan.ac.in/U01/Faculty-Photo/389---29-04-2023-11-02-59.jpg",
    "name": "Prof. Priyanka  Kotecha",
    "designation": "Assistant Professor",
    "education": "M.A. English Literature, B.Ed. English",
    "experiance": "1+ Years",
    "joining": "Apr-2023"
  },
  {
    "id": "69",
    "image": "https://darshan.ac.in/U01/Faculty-Photo/101---28-04-2023-01-51-19.jpg",
    "name": "Prof. Anil Kansagara",
    "designation": "Assistant Professor",
    "education": "M.E. (Electrical Power System)",
    "experiance": "14+ Years",
    "joining": "Jul-2009"
  },
  {
    "id": "70",
    "image": "https://darshan.ac.in/U01/Faculty-Photo/105---28-04-2023-01-51-39.jpg",
    "name": "Prof. Bhavin Kanani",
    "designation": "Assistant Professor",
    "education": "M.Tech. (Power Apparatus & Systems)",
    "experiance": "15+ Years",
    "joining": "Jul-2011"
  },
  {
    "id": "71",
    "image": "https://darshan.ac.in/U01/Faculty-Photo/96---28-04-2023-01-58-00.jpg",
    "name": "Prof. Bhavesh Dave",
    "designation": "Assistant Professor",
    "education": "M.E. (Power Electronics & Electrical Drives)",
    "experiance": "12+ Years",
    "joining": "Oct-2010"
  },
  {
    "id": "72",
    "image": "https://darshan.ac.in/U01/Faculty-Photo/49---28-04-2023-01-59-02.jpg",
    "name": "Prof. Hardik Lakhani",
    "designation": "Assistant Professor",
    "education": "M.Tech (Power Electronics & Drives)",
    "experiance": "11+ Years",
    "joining": "Jan-2013"
  },
  {
    "id": "73",
    "image": "https://darshan.ac.in/U01/Faculty-Photo/310---28-04-2023-01-31-50.jpg",
    "name": "Prof. Raj Mehta",
    "designation": "Assistant Professor",
    "education": "M.Tech (PED)",
    "experiance": "4+ Years",
    "joining": "Mar-2021"
  }
]